gcms_data_analysis/__init__.py
gcms_data_analysis/fragmenter.py
gcms_data_analysis/main.py
gcms_data_analysis/plotting.py
gcms_data_analysis-1.2.0.dist-info/METADATA
gcms_data_analysis-1.2.0.dist-info/WHEEL
gcms_data_analysis-1.2.0.dist-info/license
gcms_data_analysis-1.2.0.dist-info/top_level.txt
gcms_data_analysis-1.2.0.dist-info/RECORD
