Metadata-Version: 2.1
Name: gcms_data_analysis
Version: 1.2.0
Summary: Automatic analysis of GC-MS data
Author: Matteo Pecchi
License: MIT License
Project-URL: Homepage, https://github.com/mpecchi/gcms_data_analysis/tree/main
Project-URL: Documentation, https://gcms-data-analysis.readthedocs.io/en/latest/
Classifier: Programming Language :: Python :: 3
Classifier: License :: OSI Approved :: MIT License
Classifier: Operating System :: OS Independent
Requires-Python: >=3.8
License-File: license
Requires-Dist: numpy
Requires-Dist: pandas
Requires-Dist: matplotlib
Requires-Dist: seaborn
Requires-Dist: ele
Requires-Dist: pubchempy
Requires-Dist: rdkit
Requires-Dist: openpyxl
Requires-Dist: pyarrow
